README.rst
setup.py
django_github_log.egg-info/PKG-INFO
django_github_log.egg-info/SOURCES.txt
django_github_log.egg-info/dependency_links.txt
django_github_log.egg-info/requires.txt
django_github_log.egg-info/top_level.txt
github_log/__init__.py
github_log/admin.py
github_log/log.py
github_log/models.py
github_log/tasks.py
github_log/tests.py
github_log/views.py