Metadata-Version: 1.1
Name: django-github-log
Version: 0.1.8
Summary: Django log handler to create issue on github automatically
Home-page: UNKNOWN
Author: Seungyeon Joshua Kim(Acuros)
Author-email: acuroskr@gmail.com
License: MIT License
Platform: UNKNOWN
Classifier: Development Status :: 3 - Alpha
Classifier: Environment :: Web Environment
Classifier: Framework :: Django
Classifier: Intended Audience :: Developers
Classifier: License :: OSI Approved :: MIT License
Classifier: Operating System :: OS Independent
Classifier: Programming Language :: Python
Classifier: Topic :: Software Development :: Libraries :: Python Modules
